atom_access/__init__.py
atom_access/cli.py
atom_access/core.py
atom_access/objects.py
atom_access/utils.py
atom_access/version.py
atom_access-2.7.0.dist-info/licenses/LICENSE
atom_access-2.7.0.dist-info/METADATA
atom_access-2.7.0.dist-info/WHEEL
atom_access-2.7.0.dist-info/entry_points.txt
atom_access-2.7.0.dist-info/top_level.txt
atom_access-2.7.0.dist-info/RECORD
