Metadata-Version: 2.4
Name: atom_access
Version: 2.7.0
Summary: atom_access is a ray tracing package for addressing the steric          hindrance of molecules
Home-page: https://gitlab.com/atomaccess/atomaccess
Project-URL: Bug Tracker, https://gitlab.com/atomaccess/atomaccess/-/issues
Project-URL: Documentation, https://atomaccess.gitlab.io/atomaccess/
Classifier: Programming Language :: Python :: 3
Classifier: License :: OSI Approved :: GNU General Public License v3 (GPLv3)
Classifier: Operating System :: OS Independent
Requires-Python: >=3.10
License-File: LICENSE
Requires-Dist: numpy>=1.24.3
Requires-Dist: xyz_py>=5.7.0
Requires-Dist: plotly>=5.14.1
Requires-Dist: scikit-learn>=1.2.2
Requires-Dist: pathos>=0.3.4
Dynamic: classifier
Dynamic: description
Dynamic: description-content-type
Dynamic: home-page
Dynamic: license-file
Dynamic: project-url
Dynamic: requires-dist
Dynamic: requires-python
Dynamic: summary
